openvino_trackface/__init__.py
openvino_trackface/config.py
openvino_trackface/control.py
openvino_trackface/download_model.py
openvino_trackface/run_server.py
openvino_trackface/run_service.py
openvino_trackface/app/__init__.py
openvino_trackface/app/routes.py
openvino_trackface/model_class/__init__.py
openvino_trackface/model_class/bytetrack/__init__.py
openvino_trackface/model_class/bytetrack/core/__init__.py
openvino_trackface/model_class/bytetrack/core/launch.py
openvino_trackface/model_class/bytetrack/core/trainer.py
openvino_trackface/model_class/bytetrack/data/__init__.py
openvino_trackface/model_class/bytetrack/data/data_augment.py
openvino_trackface/model_class/bytetrack/data/data_prefetcher.py
openvino_trackface/model_class/bytetrack/data/dataloading.py
openvino_trackface/model_class/bytetrack/data/samplers.py
openvino_trackface/model_class/bytetrack/data/datasets/__init__.py
openvino_trackface/model_class/bytetrack/data/datasets/datasets_wrapper.py
openvino_trackface/model_class/bytetrack/data/datasets/mosaicdetection.py
openvino_trackface/model_class/bytetrack/data/datasets/mot.py
openvino_trackface/model_class/bytetrack/evaluators/__init__.py
openvino_trackface/model_class/bytetrack/evaluators/coco_evaluator.py
openvino_trackface/model_class/bytetrack/evaluators/evaluation.py
openvino_trackface/model_class/bytetrack/evaluators/mot_evaluator.py
openvino_trackface/model_class/bytetrack/exp/__init__.py
openvino_trackface/model_class/bytetrack/exp/base_exp.py
openvino_trackface/model_class/bytetrack/exp/build.py
openvino_trackface/model_class/bytetrack/exp/yolox_base.py
openvino_trackface/model_class/bytetrack/layers/__init__.py
openvino_trackface/model_class/bytetrack/layers/fast_coco_eval_api.py
openvino_trackface/model_class/bytetrack/models/__init__.py
openvino_trackface/model_class/bytetrack/models/darknet.py
openvino_trackface/model_class/bytetrack/models/losses.py
openvino_trackface/model_class/bytetrack/models/network_blocks.py
openvino_trackface-0.0.1.dist-info/METADATA
openvino_trackface-0.0.1.dist-info/WHEEL
openvino_trackface-0.0.1.dist-info/top_level.txt
openvino_trackface-0.0.1.dist-info/RECORD
