Metadata-Version: 2.1
Name: openvino-trackface
Version: 0.0.1
Summary: Face tracking using OpenVINO Face detection and ByteTrack model
Classifier: Programming Language :: Python :: 3
Classifier: Operating System :: OS Independent
Requires-Python: >=3.7
